spellwell/__init__.py
spellwell/cli.py
spellwell/wordlist.py
spellwell-0.1.1.dist-info/LICENSE
spellwell-0.1.1.dist-info/METADATA
spellwell-0.1.1.dist-info/WHEEL
spellwell-0.1.1.dist-info/entry_points.txt
spellwell-0.1.1.dist-info/RECORD
