Metadata-Version: 2.3
Name: spellwell
Version: 0.1.1
Summary: SpellWell is a CLI application which allows you to practice spelling using your own wordlist.
License: MIT
Author: Emil
Author-email: emil@wirely.se
Requires-Python: >=3.13
Classifier: License :: OSI Approved :: MIT License
Classifier: Programming Language :: Python :: 3
Classifier: Programming Language :: Python :: 3.13
Requires-Dist: click (>=8.1.8,<9.0.0)
Requires-Dist: rich (>=14.0.0,<15.0.0)
Project-URL: Documentation, https://github.com/ehmiiz/SpellWell
Project-URL: Homepage, https://github.com/ehmiiz/SpellWell
Project-URL: Repository, https://github.com/ehmiiz/SpellWell
